cdktf_pyplus/__init__.py
cdktf_pyplus/aws/__init__.py
cdktf_pyplus/aws/aws_util.py
cdktf_pyplus/config_aws.py
cdktf_pyplus/config_base.py
cdktf_pyplus/stack_base.py
cdktf_pyplus/util.py
cdktf_pyplus-0.0.1.dist-info/WHEEL
cdktf_pyplus-0.0.1.dist-info/METADATA
cdktf_pyplus-0.0.1.dist-info/RECORD
